bsdiff4/test_all.py
bsdiff4/__init__.py
bsdiff4/format.py
bsdiff4/cli.py
bsdiff4/core.cpython-310-darwin.so
bsdiff4-1.2.6.dist-info/RECORD
bsdiff4-1.2.6.dist-info/LICENSE
bsdiff4-1.2.6.dist-info/WHEEL
bsdiff4-1.2.6.dist-info/entry_points.txt
bsdiff4-1.2.6.dist-info/top_level.txt
bsdiff4-1.2.6.dist-info/METADATA
